pod_tools/__init__.py
pod_tools/json_schema.json
pod_tools/pod_tools.py
pod_tools/services.json
pod_tools/version.py
pod_tools-1.0.0.dist-info/METADATA
pod_tools-1.0.0.dist-info/WHEEL
pod_tools-1.0.0.dist-info/top_level.txt
pod_tools-1.0.0.dist-info/RECORD
