Metadata-Version: 2.1
Name: pod-tools
Version: 1.0.0
Summary: POD Tools services
Home-page: https://github.com/FanapSoft/pod-tools-python-sdk
Author: ReZa ZaRe
Author-email: rz.zare@gmail.com
License: MIT
Project-URL: Source, https://github.com/FanapSoft/pod-tools-python-sdk
Project-URL: Documentation, http://docs.pod.ir/v1.0.0.2/PODSDKs/python/5950/tools
Project-URL: Tracker, https://github.com/FanapSoft/pod-tools-python-sdk/issues
Keywords: POD,tools,pay bill,pod sdk
Platform: UNKNOWN
Classifier: Natural Language :: Persian
Classifier: Natural Language :: English
Classifier: Programming Language :: Python
Classifier: Programming Language :: Python :: 2
Classifier: Programming Language :: Python :: 2.7
Classifier: Programming Language :: Python :: 3
Classifier: Programming Language :: Python :: 3.5
Classifier: Programming Language :: Python :: 3.6
Classifier: Programming Language :: Python :: 3.7
Requires-Python: >=2.7
Requires-Dist: pod-base (<2,>=1.0.3)
